xenharmlib/__init__.py
xenharmlib/exc.py
xenharmlib/play.py
xenharmlib/core/__init__.py
xenharmlib/core/constants.py
xenharmlib/core/enharm_strategies.py
xenharmlib/core/freq_repr.py
xenharmlib/core/frequencies.py
xenharmlib/core/interval.py
xenharmlib/core/interval_seq.py
xenharmlib/core/masks.py
xenharmlib/core/notation.py
xenharmlib/core/note_interval_seq.py
xenharmlib/core/note_scale.py
xenharmlib/core/notes.py
xenharmlib/core/origin_context.py
xenharmlib/core/pitch.py
xenharmlib/core/pitch_interval_seq.py
xenharmlib/core/pitch_scale.py
xenharmlib/core/protocols.py
xenharmlib/core/scale.py
xenharmlib/core/symbols.py
xenharmlib/core/tunings.py
xenharmlib/core/utils.py
xenharmlib/export/__init__.py
xenharmlib/export/audio.py
xenharmlib/export/scl.py
xenharmlib/notation/__init__.py
xenharmlib/notation/updown.py
xenharmlib/notation/western.py
xenharmlib/periodic/__init__.py
xenharmlib/periodic/intervals.py
xenharmlib/periodic/iter.py
xenharmlib/periodic/match.py
xenharmlib/periodic/utils.py
xenharmlib/setc/__init__.py
xenharmlib/setc/nf.py
xenharmlib/setc/primeform.py
xenharmlib-0.3.0.dist-info/METADATA
xenharmlib-0.3.0.dist-info/WHEEL
xenharmlib-0.3.0.dist-info/licenses/LICENCE
xenharmlib-0.3.0.dist-info/RECORD
