Metadata-Version: 2.4
Name: xenharmlib
Version: 0.3.0
Summary: A library for microtonal music theory
Project-URL: Documentation, https://xenharmlib.readthedocs.io/en/latest/
Project-URL: Homepage, https://gitlab.com/retooth/xenharmlib
Project-URL: Issues, https://gitlab.com/retooth/xenharmlib/-/issues
Author-email: Fabian Vallon <fabian.vallon@gmail.com>
License-File: LICENCE
Keywords: atonal theory,diatonic set theory,microtonal,microtonality,music,music theory,musicology,post-tonal theory,xenharmonics
Classifier: Development Status :: 4 - Beta
Classifier: License :: OSI Approved :: GNU General Public License v3 or later (GPLv3+)
Classifier: Operating System :: OS Independent
Classifier: Programming Language :: Python :: 3
Classifier: Topic :: Artistic Software
Classifier: Topic :: Education
Classifier: Topic :: Multimedia :: Sound/Audio
Requires-Python: >=3.11.7
Requires-Dist: numpy<2,>=1.26.4
Requires-Dist: scipy<2,>=1.12.0
Requires-Dist: sounddevice<1,>=0.4.6
Requires-Dist: sympy==1.12
